{"_path":"/design-system/develop/usage","_dir":"develop","_draft":false,"_partial":false,"_locale":"","title":"Usage","description":"Ripple components can be used in several different ways depending on your project needs.","layout":"page","links":[{"text":"Github","url":"https://github.com/dpc-sdp/ripple-framework"},{"text":"Storybook","url":"/storybook"}],"body":{"type":"root","children":[{"type":"element","tag":"h2","props":{"id":"using-ripple-ui-components"},"children":[{"type":"text","value":"Using Ripple UI components"}]},{"type":"element","tag":"p","props":{},"children":[{"type":"text","value":"Whilst Ripple is built to implement sites using a framework built on Vue JS and Nuxt, its modular architecture allows adopting different parts depending on your requirements."}]},{"type":"element","tag":"p","props":{},"children":[{"type":"element","tag":"img","props":{"alt":"ripple is made up of Figma design, CSS styles, Vue JS components and Nuxt JS Sites","src":"/assets/img/modules/rpl-modules.png"},"children":[]}]},{"type":"element","tag":"p","props":{},"children":[{"type":"text","value":"Ripple UI libraries are usable in the following contexts:"}]},{"type":"element","tag":"p","props":{},"children":[{"type":"element","tag":"svg","props":{"id":"docs-sprite","ariaHidden":"true","className":["rpl-svg-sprite--hidden"]},"children":[{"type":"element","tag":"defs","props":{},"children":[{"type":"element","tag":"symbol","props":{"xmlns":"http://www.w3.org/2000/svg","id":"icon-check","viewBox":"0 0 24 24"},"children":[{"type":"element","tag":"path","props":{"d":"M22.9.4c-1.1-.7-2.6-.4-3.3.8L9.2 17.8l-5.1-5.1c-.9-.9-2.5-.9-3.4 0s-.9 2.5 0 3.4l7.2 7.2c1.1 1.1 2.9.9 3.7-.4l12-19.2c.7-1.2.4-2.6-.7-3.3z"},"children":[]}]}]}]}]},{"type":"text","value":"\n\n\n\n\n\n\n\n\n\n\n\n\n\n\n\n\n\n\n\n\n\n\n\n\n\n\n"},{"type":"element","tag":"table","props":{},"children":[{"type":"element","tag":"thead","props":{},"children":[{"type":"element","tag":"tr","props":{},"children":[{"type":"element","tag":"th","props":{},"children":[{"type":"text","value":"Library"}]},{"type":"element","tag":"th","props":{},"children":[{"type":"text","value":"CSS styles"}]},{"type":"element","tag":"th","props":{},"children":[{"type":"text","value":"Vue Components"}]},{"type":"element","tag":"th","props":{},"children":[{"type":"text","value":"Ripple Framework (Nuxt)"}]},{"type":"element","tag":"th","props":{},"children":[{"type":"text","value":"Web components"}]}]}]},{"type":"element","tag":"tbody","props":{},"children":[{"type":"element","tag":"tr","props":{},"children":[{"type":"element","tag":"td","props":{},"children":[{"type":"text","value":"Ripple UI Core"}]},{"type":"element","tag":"td","props":{},"children":[{"type":"element","tag":"svg","props":{"width":"12","height":"12"},"children":[{"type":"element","tag":"title","props":{},"children":[{"type":"text","value":"supported"}]},{"type":"element","tag":"use","props":{"xLinkHref":"#icon-check"},"children":[]}]}]},{"type":"element","tag":"td","props":{},"children":[{"type":"element","tag":"svg","props":{"width":"12","height":"12"},"children":[{"type":"element","tag":"title","props":{},"children":[{"type":"text","value":"supported"}]},{"type":"element","tag":"use","props":{"xLinkHref":"#icon-check"},"children":[]}]}]},{"type":"element","tag":"td","props":{},"children":[{"type":"element","tag":"svg","props":{"width":"12","height":"12"},"children":[{"type":"element","tag":"title","props":{},"children":[{"type":"text","value":"supported"}]},{"type":"element","tag":"use","props":{"xLinkHref":"#icon-check"},"children":[]}]}]},{"type":"element","tag":"td","props":{},"children":[{"type":"text","value":"Partial support"}]}]},{"type":"element","tag":"tr","props":{},"children":[{"type":"element","tag":"td","props":{},"children":[{"type":"text","value":"Ripple UI Forms"}]},{"type":"element","tag":"td","props":{},"children":[{"type":"element","tag":"svg","props":{"width":"12","height":"12"},"children":[{"type":"element","tag":"title","props":{},"children":[{"type":"text","value":"supported"}]},{"type":"element","tag":"use","props":{"xLinkHref":"#icon-check"},"children":[]}]}]},{"type":"element","tag":"td","props":{},"children":[{"type":"element","tag":"svg","props":{"width":"12","height":"12"},"children":[{"type":"element","tag":"title","props":{},"children":[{"type":"text","value":"supported"}]},{"type":"element","tag":"use","props":{"xLinkHref":"#icon-check"},"children":[]}]}]},{"type":"element","tag":"td","props":{},"children":[{"type":"element","tag":"svg","props":{"width":"12","height":"12"},"children":[{"type":"element","tag":"title","props":{},"children":[{"type":"text","value":"supported"}]},{"type":"element","tag":"use","props":{"xLinkHref":"#icon-check"},"children":[]}]}]},{"type":"element","tag":"td","props":{},"children":[{"type":"element","tag":"svg","props":{"width":"12","height":"12"},"children":[{"type":"element","tag":"title","props":{},"children":[{"type":"text","value":"not supported"}]},{"type":"element","tag":"use","props":{"xLinkHref":"#icon-cancel"},"children":[]}]}]}]}]}]},{"type":"element","tag":"h3","props":{"id":"using-in-an-sdp-website"},"children":[{"type":"text","value":"Using in an SDP website"}]},{"type":"element","tag":"blockquote","props":{},"children":[{"type":"element","tag":"p","props":{},"children":[{"type":"text","value":"If you are using Ripple 2 to build a site on the SDP platform, the UI libraries will be included automatically when scaffolding your project."}]},{"type":"element","tag":"p","props":{},"children":[{"type":"text","value":"For documentation on using Ripple with Nuxt in SDP sites, visit the "},{"type":"element","tag":"a","props":{"href":"/framework"},"children":[{"type":"text","value":"Ripple Framework documentation"}]}]}]},{"type":"element","tag":"h3","props":{"id":"github-packages"},"children":[{"type":"text","value":"Github Packages"}]},{"type":"element","tag":"p","props":{},"children":[{"type":"text","value":"Ripple 2 is hosted publicly on Github Packages (ghcr) under the "},{"type":"element","tag":"strong","props":{},"children":[{"type":"text","value":"@dpc/sdp"}]},{"type":"text","value":" namespace, please read these "},{"type":"element","tag":"a","props":{"href":"/design-system/develop/usage/access-to-github-packages"},"children":[{"type":"text","value":"setup instructions for accessing Github Packages"}]},{"type":"text","value":"."}]}],"toc":{"title":"","searchDepth":2,"depth":2,"links":[{"id":"using-ripple-ui-components","depth":2,"text":"Using Ripple UI components","children":[{"id":"using-in-an-sdp-website","depth":3,"text":"Using in an SDP website"},{"id":"github-packages","depth":3,"text":"Github Packages"}]}]}},"_type":"markdown","_id":"content:design-system:3.develop:3.usage.md","_source":"content","_file":"design-system/3.develop/3.usage.md","_extension":"md"}