[{"_path":"/design-system/design/our-design-principles","_dir":"design","_draft":false,"_partial":false,"_locale":"","title":"Our design principles","description":"There are 4 design principles that are the foundation of the Ripple Design System.","layout":"page","label":"Core","_type":"markdown","_id":"content:design-system:2.design:2.our-design-principles.md","_source":"content","_file":"design-system/2.design/2.our-design-principles.md","_extension":"md"},{"_path":"/design-system/design/theming-guidance-for-designers","_dir":"design","_draft":false,"_partial":false,"_locale":"","title":"Theming guidance for designers","description":null,"layout":"page","label":"Core","_type":"markdown","_id":"content:design-system:2.design:4.theming-guidance-for-designers.md","_source":"content","_file":"design-system/2.design/4.theming-guidance-for-designers.md","_extension":"md"}]