[{"_path":"/framework/key-concepts/content-types","_dir":"key-concepts","_draft":false,"_partial":false,"_locale":"","title":"Content types","description":"Implementing content type specific page layouts","layout":"page","links":[{"text":"Drupal content types","url":"https://www.drupal.org/docs/7/understanding-drupal/content-types"}],"_type":"markdown","_id":"content:framework:2.key-concepts:4.content-types.md","_source":"content","_file":"framework/2.key-concepts/4.content-types.md","_extension":"md"},{"_path":"/framework/guides/migrating","_dir":"guides","_draft":false,"_partial":false,"_locale":"","title":"Migrating from Ripple 1.x","description":"This guide is intended to outline the process of updating SDP sites using Ripple 1.x to Ripple 2. It is intended for developers tasked with porting Ripple 1 sites and features to Ripple 2.","layout":"page","_type":"markdown","_id":"content:framework:3.guides:1.migrating.md","_source":"content","_file":"framework/3.guides/1.migrating.md","_extension":"md"}]