{"_path":"/design-system/components/tag","_dir":"components","_draft":false,"_partial":false,"_locale":"","_empty":false,"title":"Tag","description":"The Tag component adds, and draws attention to, a category name for your content.","layout":"page","label":"Core","body":{"type":"root","children":[{"type":"element","tag":"h2","props":{"id":"usage"},"children":[{"type":"text","value":"Usage"}]},{"type":"element","tag":"p","props":{},"children":[{"type":"text","value":"Use tags to help categorise content. Tags help users to scan and find content that's relevant to them."}]},{"type":"element","tag":"p","props":{},"children":[{"type":"text","value":"Content can have more than one category or theme. Using the tag component helps indicate this to the user."}]},{"type":"element","tag":"p","props":{},"children":[{"type":"text","value":"When naming tags, use a noun or adjective. Don't use verbs as a user may confuse the tag with an action."}]},{"type":"element","tag":"docs-example","props":{"id":"core-containers-tag--neutral"},"children":[]},{"type":"element","tag":"h3","props":{"id":"when-and-how-to-use"},"children":[{"type":"text","value":"When and how to use"}]},{"type":"element","tag":"ul","props":{},"children":[{"type":"element","tag":"li","props":{},"children":[{"type":"text","value":"Use keywords."}]},{"type":"element","tag":"li","props":{},"children":[{"type":"text","value":"Use to draw attention to a category of content or information."}]},{"type":"element","tag":"li","props":{},"children":[{"type":"text","value":"Use nouns or adjectives."}]}]},{"type":"element","tag":"h3","props":{"id":"when-and-how-not-to-use"},"children":[{"type":"text","value":"When and how not to use"}]},{"type":"element","tag":"ul","props":{},"children":[{"type":"element","tag":"li","props":{},"children":[{"type":"text","value":"Don't use punctuation."}]},{"type":"element","tag":"li","props":{},"children":[{"type":"text","value":"Don't overuse tags."}]},{"type":"element","tag":"li","props":{},"children":[{"type":"text","value":"Don't use icons in the tags."}]},{"type":"element","tag":"li","props":{},"children":[{"type":"text","value":"Don't use as a heading."}]},{"type":"element","tag":"li","props":{},"children":[{"type":"text","value":"Don't use more than 2 words."}]},{"type":"element","tag":"li","props":{},"children":[{"type":"text","value":"Don't use as a link or action."}]}]},{"type":"element","tag":"hr","props":{},"children":[]},{"type":"element","tag":"h2","props":{"id":"variants"},"children":[{"type":"text","value":"Variants"}]},{"type":"element","tag":"p","props":{},"children":[{"type":"text","value":"Tags have 2 variants:"}]},{"type":"element","tag":"ul","props":{},"children":[{"type":"element","tag":"li","props":{},"children":[{"type":"text","value":"default, for use on neutral backgrounds"}]},{"type":"element","tag":"li","props":{},"children":[{"type":"text","value":"neutral, for use on white backgrounds."}]}]},{"type":"element","tag":"h3","props":{"id":"default"},"children":[{"type":"text","value":"Default"}]},{"type":"element","tag":"docs-example","props":{"id":"core-containers-tag--default-story"},"children":[]},{"type":"element","tag":"h3","props":{"id":"neutral"},"children":[{"type":"text","value":"Neutral"}]},{"type":"element","tag":"p","props":{},"children":[{"type":"text","value":"Use the reverse variant when the chip appears on the primary colour."}]},{"type":"element","tag":"docs-example","props":{"id":"core-containers-tag--neutral"},"children":[]}],"toc":{"title":"","searchDepth":2,"depth":2,"links":[{"id":"usage","depth":2,"text":"Usage","children":[{"id":"when-and-how-to-use","depth":3,"text":"When and how to use"},{"id":"when-and-how-not-to-use","depth":3,"text":"When and how not to use"}]},{"id":"variants","depth":2,"text":"Variants","children":[{"id":"default","depth":3,"text":"Default"},{"id":"neutral","depth":3,"text":"Neutral"}]}]}},"_type":"markdown","_id":"content:design-system:5.components:tag.md","_source":"content","_file":"design-system/5.components/tag.md","_extension":"md"}